<?xml version="1.0" encoding="UTF-8" standalone="yes"?>
<VerifyJWT async="false" continueOnError="false" enabled="true" name="VerifyIdToken">
    <DisplayName>VerifyIdToken</DisplayName>
    <FaultRules/>
    <Properties/>
    <AdditionalClaims/>
    <AdditionalHeaders/>
    <Algorithm>RS256</Algorithm>
    <IgnoreUnresolvedVariables>false</IgnoreUnresolvedVariables>
    <Issuer ref="okta.issuer"></Issuer>
    <PublicKey>
        <JWKS ref="cached.okta.jwks"></JWKS>
    </PublicKey>
    <Source>id_token</Source>
</VerifyJWT>
